HDL_SRC/CORE/alu/alu.v
/*
 * *****************************************************************
 * File: alu.v
 * Category: alu
 * File Created: 2018/12/19 23:48
 * Author: Takuya Shono ( ta.shono+1@gmail.com )
 * *****
 * Last Modified: 2019/01/11 02:24
 * Modified By: Takuya Shono ( ta.shono+1@gmail.com )
 * *****
 * Copyright 2018 - 2018  Project RockWave
 * *****************************************************************
 * Description:
 *   
 * *****************************************************************
 * HISTORY:
 * Date      	By        	Comments
 * ----------	----------	----------------------------------------
 * 2018/12/19	Takuya Shono	First Version
 * *****************************************************************
 */

module alu (
    aluin1,
    aluin2,
    funct3,
    funct7,
    aluout
    );
    
    parameter XLEN = 32;

    input  wire signed [XLEN-1:0] aluin1;
    input  wire signed [XLEN-1:0] aluin2;
    input  wire [2:0] funct3;
    input  wire funct7;
    output wire [XLEN-1:0] aluout;
    wire [3:0] funct73;

    assign funct73 = {funct7,funct3};
    
    function [XLEN-1:0] calc( 
        input [3:0] funct73,
        input signed [XLEN-1:0] aluin1,
        input signed [XLEN-1:0] aluin2
        );

        begin
            case( funct73 )
                   4'b0000  : calc = aluin1 + aluin2; //ADD//ADDI 加算
                   4'b1000  : calc = aluin1 - aluin2; //SUB 減算
                   4'b0001  : calc = aluin1 << aluin2 [4:0]; //SLL//SLLI 左シフト
                   4'bX010  : calc = (aluin1 < aluin2)? 1:0; //SLT //SLTI
                   4'bX011  : calc = ($unsigned(aluin1) < $unsigned(aluin2))? 1:0; //SLTU //SLTIU
                   4'bX100  : calc = aluin1 ^ aluin2; //XOR//XORI 排他的論理和
                   4'b0101  : calc = aluin1 >> aluin2 [4:0]; //SRL//SRLI 右シフト
                   4'b1101  : calc = aluin1 >>> aluin2 [4:0]; //SRA//SRAI 右算術シフト
                   4'bX110  : calc = aluin1 | aluin2; //OR//ORI 論理和                   
                   4'bX111  : calc = aluin1 & aluin2; //AND//ANDI 論理積
                   default : calc = 32'hXXXX_XXXX;
            endcase
        end
    endfunction

    assign aluout = calc( funct73, aluin1, aluin2);

endmodule // alu

HDL_SIM/CORE/alu/alu_tb.v
 /*
 * *****************************************************************
 * File: alu_tb.v
 * Category: alu
 * File Created: 2018/12/19 12:12
 * Author: Takuya Shono ( ta.shono+1@gmail.com )
 * *****
 * Last Modified: 2018/12/19 12:12
 * Modified By: Takuya Shono ( ta.shono+1@gmail.com )
 * *****
 * Copyright 2018 - 2018  Project RockWave
 * *****************************************************************
 * Description:
 *   
 * *****************************************************************
 * HISTORY:
 * Date      	By        	Comments
 * ----------	----------	----------------------------------------
 * 2018/12/19	Takuya Shono	First Version
 * *****************************************************************
 */

module alu_tb;

reg [31:0] aluin1;
reg [31:0] aluin2;
reg [2:0] funct3;
reg funct7;
wire [31:0] aluout;

//1周期1000unit
parameter STEP = 1;

alu test(
   aluin1, aluin2, funct3, funct7, aluout
);

initial begin

    funct3 = 3'b000;
    funct7 = 1'b0;
    aluin1 = 32'b0000_0000_0000_0000_0000_0000_0000_0000;
    aluin2 = 32'b0000_0000_0000_0000_0000_0000_0000_0000;

    #STEP
    funct3 = 3'b000;
    funct7 = 1'b0;
    aluin1 = 32'b0000_0000_0000_0000_0000_0000_0000_0000;
    aluin2 = 32'b0000_0000_0000_0000_0000_0000_0000_0000;

    #STEP
    funct3 = 3'b000;
    funct7 = 1'b0;
    aluin1 = 32'b0000_0000_0000_0000_0000_0000_0000_0111;
    aluin2 = 32'b0000_0000_0000_0000_0000_0000_0000_1010;

    #STEP    funct3 = 3'b001; funct7 = 1'b0;
    #STEP    funct3 = 3'b010; funct7 = 1'b0;
    #STEP    funct3 = 3'b011; funct7 = 1'b0;    
    #STEP    funct3 = 3'b100; funct7 = 1'b0;
    #STEP    funct3 = 3'b101; funct7 = 1'b0;
    #STEP    funct3 = 3'b110; funct7 = 1'b0;
    #STEP    funct3 = 3'b111; funct7 = 1'b0;
    #STEP    funct3 = 3'bXXX; funct7 = 1'b0;
    #STEP    funct3 = 3'b000; funct7 = 1'bX;

    #STEP    funct3 = 3'b001; funct7 = 1'b1;
    #STEP    funct3 = 3'b010; funct7 = 1'b1;
    #STEP    funct3 = 3'b011; funct7 = 1'b1;    
    #STEP    funct3 = 3'b100; funct7 = 1'b1;
    #STEP    funct3 = 3'b101; funct7 = 1'b1;
    #STEP    funct3 = 3'b110; funct7 = 1'b1;
    #STEP    funct3 = 3'b111; funct7 = 1'b1;
    #STEP    funct3 = 3'bXXX; funct7 = 1'b1;

    #STEP    funct3 = 3'bXXX; funct7 = 1'bX;

end

/* 表示 */
initial begin
 $dumpfile("alu.vcd");
    $dumpvars(0,alu_tb);
    $monitor(" STEP=%d funct3= %b funct7= %b aluin1=%b aluin2=%b aluout=%b ",STEP,funct3,funct7,aluin1,aluin2,aluout);
end

endmodule

HDL_SIM/CORE/alu/alu.vcd
$date
	Fri Jan 11 02:21:30 2019
$end
$version
	Icarus Verilog
$end
$timescale
	1s
$end
$scope module alu_tb $end
$var wire 32 ! aluout [31:0] $end
$var reg 32 " aluin1 [31:0] $end
$var reg 32 # aluin2 [31:0] $end
$var reg 3 $ funct3 [2:0] $end
$var reg 1 % funct7 $end
$scope module test $end
$var wire 32 & aluin1 [31:0] $end
$var wire 32 ' aluin2 [31:0] $end
$var wire 3 ( funct3 [2:0] $end
$var wire 1 % funct7 $end
$var wire 4 ) funct73 [3:0] $end
$var wire 32 * aluout [31:0] $end
$scope function calc $end
$var reg 32 + aluin1 [31:0] $end
$var reg 32 , aluin2 [31:0] $end
$var reg 32 - calc [31:0] $end
$var reg 4 . funct73 [3:0] $end
$upscope $end
$upscope $end
$upscope $end
$enddefinitions $end
#0
$dumpvars
b0 .
b0 -
b0 ,
b0 +
b0 *
b0 )
b0 (
b0 '
b0 &
0%
b0 $
b0 #
b0 "
b0 !
$end
#1
b10000000000000000000000000010001 !
b10000000000000000000000000010001 *
b10000000000000000000000000010001 -
b10000000000000000000000000001010 ,
b111 +
b10000000000000000000000000001010 #
b10000000000000000000000000001010 '
b111 "
b111 &
#3
b1111111111111111111111111111101 !
b1111111111111111111111111111101 *
b1111111111111111111111111111101 -
b1000 .
b1000 )
1%
#4
b1110000000000 !
b1110000000000 *
b1110000000000 -
b1 .
b1 $
b1 (
b1 )
0%
#5
bx !
bx *
bx -
b10 .
b10 )
b10 $
b10 (
#6
b11 .
b11 )
b11 $
b11 (
#7
b100 .
b100 )
b100 $
b100 (
#8
b110 .
b110 )
b110 $
b110 (
#9
b111 .
b111 )
b111 $
b111 (
#10
b10000000000000000000000000000111 +
bx .
b10000000000000000000000000000111 "
b10000000000000000000000000000111 &
bx $
bx (
bx )
x%
#11
b1000000000000000000000 !
b1000000000000000000000 *
b1000000000000000000000 -
b101 .
b101 $
b101 (
b101 )
0%
#12
b11111111111000000000000000000000 !
b11111111111000000000000000000000 *
b11111111111000000000000000000000 -
b1101 .
b1101 )
1%
