HDL_SRC/CORE/core_general.vh
/*
 * *****************************************************************
 * File: core_general.vh
 * Category: CORE
 * File Created: 2018/12/18 04:23
 * Author: Masaru Aoki ( masaru.aoki.1972@gmail.com )
 * *****
 * Last Modified: 2019/01/24 04:29
 * Modified By: Masaru Aoki ( masaru.aoki.1972@gmail.com )
 * *****
 * Copyright 2018 - 2018  Project RockWave
 * *****************************************************************
 * Description:
 *   全体で使用する定義
 * *****************************************************************
 * HISTORY:
 * Date      	By        	Comments
 * ----------	----------	----------------------------------------
 * 2019/01/24	Masaru Aoki	64bitの記述を追加
 * 2019/01/09	kidtak51	  各制御ブロックの出力段のFlipFlopを除去するための定義を追加した
 * 2019/1/4	  kidtak51	  parameter名一部修正
 * 2018/12/28	Masaru Aoki	FUNCT3 / DataMemWE / JumpEn 追加
 * 2018/12/18	Masaru Aoki	First Version
 * *****************************************************************
 */

//    `define RV64I

    // CPU Register Bit Size
  `ifdef RV64I
      parameter XLEN = 64;
  `else
      parameter XLEN = 32;
  `endif
    
    /////////////////////////////////////////////
    // Instruction Memory
    /////////////////////////////////////////////
    // InstMemory Data Width
    parameter DWIDTH = XLEN;
    // InstMemory Address Width
    parameter AWIDTH = 12;
    // InstMemory Words size
    parameter WORDS = (2**AWIDTH);
    // Reset Vector
    parameter RESET_VECTOR = 32'h8000_0000;

    /////////////////////////////////////////////
    // Doecode
    /////////////////////////////////////////////
    parameter OPLEN = 9;

    // RS1/RS2
    parameter USE_ALU_IN1_BIT = 0;
      parameter USE_ALU_IN1_PC      = 0;
      parameter USE_ALU_IN1_RS1DATA = 1;
    parameter USE_ALU_IN2_BIT = 1;
      parameter USE_ALU_IN2_IMM     = 0;
      parameter USE_ALU_IN2_RS2DATA = 1;

    // RD
    parameter USE_RD_BIT_L = 2;
    parameter USE_RD_BIT_M = 3;
      parameter USE_RD_ALU    = 2'b00;
      parameter USE_RD_PC     = 2'b01;
      parameter USE_RD_MEMORY = 2'b10;
      parameter USE_RD_COMP   = 2'b11;
   
    // funct3
    parameter FUNCT3_BIT_L = 4;
    parameter FUNCT3_BIT_M = 6;
      // LOAD / STORE
      parameter FUNCT3_B = 3'b000;
      parameter FUNCT3_H = 3'b001;
      parameter FUNCT3_W = 3'b010;
      parameter FUNCT3_D = 3'b011;      // RV64
      parameter FUNCT3_BU = 3'b100;
      parameter FUNCT3_HU = 3'b101;
      parameter FUNCT3_WU = 3'b110;     // RV64
      // BRANCH
      parameter FUNCT3_BEQ  = 3'b000;
      parameter FUNCT3_BNE  = 3'b001;
      parameter FUNCT3_JUMP = 3'b010;  // Must Jump
      parameter FUNCT3_BLT  = 3'b100;
      parameter FUNCT3_BGE  = 3'b101;
      parameter FUNCT3_BLTU = 3'b110;
      parameter FUNCT3_BGEU = 3'b111;
      // OP
      parameter FUNCT3_SLT  = 3'b010;
      parameter FUNCT3_SLTU = 3'b011;

    // Data Memory Write Enable
    parameter DATA_MEM_WE_BIT = 7;

    // Jump Enable
    parameter JUMP_EN_BIT = 8;

    /////////////////////////////////////////////
    // Common
    /////////////////////////////////////////////
    //以下をアンコメントすると、Decodeブロック, Executeブロック, Memoryブロックの出力段FFを除去する
    //`define OUT_FLIPFLOP_REMOVE

HDL_SRC/CORE/alu/alu.v
/*
 * *****************************************************************
 * File: alu.v
 * Category: alu
 * File Created: 2018/12/19 23:48
 * Author: Takuya Shono ( ta.shono+1@gmail.com )
 * *****
 * Last Modified: 2019/01/14 24:00
 * Modified By: Takuya Shono ( ta.shono+1@gmail.com )
 * *****
 * Copyright 2018 - 2018  Project RockWave
 * *****************************************************************
 * Description:
 *   
 * *****************************************************************
 * HISTORY:
 * Date      	By        	Comments
 * ----------	----------	----------------------------------------
 * 2018/12/19	Takuya Shono	First Version
 * *****************************************************************
 */

module alu (
    aluin1,
    aluin2,
    funct_alu,
    aluout
    );
    
    parameter XLEN = 32;

    input  wire signed [XLEN-1:0] aluin1; //alu入力信号1
    input  wire signed [XLEN-1:0] aluin2; //alu入力信号2
    input  wire [3:0] funct_alu; //alu演算器選択信号
    output wire [XLEN-1:0] aluout; //alu演算結果信号

    function [XLEN-1:0] calc( 
        input signed [XLEN-1:0] aluin1,
        input signed [XLEN-1:0] aluin2,
        input funct_alu
        );

        begin
            case( funct_alu )
                   4'b0000  : calc = aluin1 + aluin2; //ADD//ADDI 加算
                   4'b1000  : calc = aluin1 - aluin2; //SUB 減算
                   4'b0001  : calc = aluin1 << aluin2 [4:0]; //SLL//SLLI 左シフト
                   4'bX010  : calc = (aluin1 < aluin2)? 1:0; //SLT //SLTI
                   4'bX011  : calc = ($unsigned(aluin1) < $unsigned(aluin2))? 1:0; //SLTU //SLTIU
                   4'bX100  : calc = aluin1 ^ aluin2; //XOR//XORI 排他的論理和
                   4'b0101  : calc = aluin1 >> aluin2 [4:0]; //SRL//SRLI 右シフト
                   4'b1101  : calc = aluin1 >>> aluin2 [4:0]; //SRA//SRAI 右算術シフト
                   4'bX110  : calc = aluin1 | aluin2; //OR//ORI 論理和                   
                   4'bX111  : calc = aluin1 & aluin2; //AND//ANDI 論理積
                   default : calc = 32'hXXXX_XXXX;
            endcase
        end
    endfunction

    assign aluout = calc( aluin1, aluin2, funct_alu);

endmodule // alu

HDL_SIM/CORE/alu/alu_tb.v
 /*
 * *****************************************************************
 * File: alu_tb.v
 * Category: alu
 * File Created: 2018/12/19 12:12
 * Author: Takuya Shono ( ta.shono+1@gmail.com )
 * *****
 * Last Modified: 2018/12/19 12:12
 * Modified By: Takuya Shono ( ta.shono+1@gmail.com )
 * *****
 * Copyright 2018 - 2018  Project RockWave
 * *****************************************************************
 * Description:
 *              演算を行う
 * *****************************************************************
 * HISTORY:
 * Date      	By        	Comments
 * ----------	----------	----------------------------------------
 * 2018/12/19	Takuya Shono	First Version
 * *****************************************************************
 */

module alu_tb;

`include "core_general.vh"

reg [XLEN-1:0] aluin1;
reg [XLEN-1:0] aluin2;
reg [3:0] funct_alu;
wire [XLEN-1:0] aluout;


//1周期1000unit
parameter STEP = 1;

alu test(
   .aluin1(aluin1), .aluin2(aluin2),
   .funct_alu(funct_alu), .aluout(aluout)
);

initial begin

    funct_alu = 4'b0000;
    aluin1 = 32'b0000_0000_0000_0000_0000_0000_0000_0000;
    aluin2 = 32'b0000_0000_0000_0000_0000_0000_0000_0000;

    #STEP
    funct_alu = 4'b0000;
    aluin1 = 32'b0000_0000_0000_0000_0000_0000_0001_0111;
    aluin2 = 32'b0000_0000_0000_0000_0000_0000_0000_1010;

/* add */       #STEP    funct_alu = 4'b0000;   #STEP assert_calc(aluout, 32'b0000_0000_0000_0000_0000_0000_0010_0001, "ADD");
/* sub */       #STEP    funct_alu = 4'b1000;   #STEP assert_calc(aluout, 32'b0000_0000_0000_0000_0000_0000_0000_1101, "SUB");
/* SLL/SLLI */  #STEP    funct_alu = 4'b0001;   #STEP assert_calc(aluout, 32'b0000_0000_0000_0000_0101_1100_0000_0000, "SLL/SLLI"); 
/* SLL/SLLI */  #STEP    funct_alu = 4'b1001;   #STEP assert_calc(aluout, 32'b0000_0000_0000_0000_0101_1100_0000_0000, "SLL/SLLI"); 
/* XOR */       #STEP    funct_alu = 4'b0100;   #STEP assert_calc(aluout, 32'b0000_0000_0000_0000_0000_0000_0001_1101, "XOR"); 
/* XOR */       #STEP    funct_alu = 4'b1100;   #STEP assert_calc(aluout, 32'b0000_0000_0000_0000_0000_0000_0001_1101, "XOR");
/* OR */        #STEP    funct_alu = 4'b0110;   #STEP assert_calc(aluout, 32'b0000_0000_0000_0000_0000_0000_0001_1111, "OR"); 
/* OR */        #STEP    funct_alu = 4'b1110;   #STEP assert_calc(aluout, 32'b0000_0000_0000_0000_0000_0000_0001_1111, "OR"); 
/* AND */       #STEP    funct_alu = 4'b0111;   #STEP assert_calc(aluout, 32'b0000_0000_0000_0000_0000_0000_0000_0010, "AND"); 
/* AND */       #STEP    funct_alu = 4'b1111;   #STEP assert_calc(aluout, 32'b0000_0000_0000_0000_0000_0000_0000_0010, "AND"); 

    #STEP
    aluin1 = 32'b1000_0000_0000_0000_0000_0000_0001_0101;
    aluin2 = 32'b0000_0000_0000_0000_0000_0000_0000_0011;
/* SRL/SRLI */  #STEP    funct_alu = 4'b0101;   #STEP assert_calc(aluout, 32'b0001_0000_0000_0000_0000_0000_0000_0010, "SRL/SRLI"); 
/* SRA/SRAI */  #STEP    funct_alu = 4'b1101;   #STEP assert_calc(aluout, 32'b1111_0000_0000_0000_0000_0000_0000_0010, "SRA/SRAI"); 

    #STEP
    aluin1 = 32'b1000_0000_0000_0000_0000_0000_0001_0101;
    aluin2 = 32'b1000_0000_0000_0000_0000_0000_0001_0001;
/* SRA/SRAI */  #STEP    funct_alu = 4'b1101;   #STEP assert_calc(aluout, 32'b1111_1111_1111_1111_1100_0000_0000_0000, "SRA/SRAI"); 

    #STEP
    aluin1 = 32'b1000_0000_0000_0000_0000_0000_0001_0101;
    aluin2 = 32'b1000_0000_0000_0000_0000_0000_0000_0001;
/* SRA/SRAI */  #STEP    funct_alu = 4'b1101;   #STEP assert_calc(aluout, 32'b1100_0000_0000_0000_0000_0000_0000_1010, "SRA/SRAI"); 



//xxxx
    #STEP
    aluin1 = 32'b1000_0000_0000_0000_0000_0000_0001_0101;
    aluin2 = 32'b0000_0000_0000_0000_0000_0000_0000_0011;
/* xxxx */      #STEP    funct_alu = 4'b0011;   #STEP assert_calc(aluout, 32'bxxxx_xxxx_xxxx_xxxx_xxxx_xxxx_xxxx_xxxx, "xxxx"); 

end

task assert_calc;
    input [XLEN-1:0] a;
    input [XLEN-1:0] b;
    input [0:8*10-1] message;
    begin
        if(a === b) begin
            $display("       OK (%b,%b,%s)", a, b, message);
        end
        else begin
            $display("Assert NG (%b,%b,%s)", a, b, message);
            $finish;
        end
    end
endtask

/* 表示 */
initial begin
 $dumpfile("alu.vcd");
    $dumpvars(0,alu_tb);
    $monitor(" STEP=%d\n funct_alu= %b\n aluin1=%b\n aluin2=%b\n aluout=%b\n ",$time,funct_alu,aluin1,aluin2,aluout);
end

endmodule

HDL_SIM/CORE/alu/alu.vcd
$date
	Tue Jan 15 12:33:29 2019
$end
$version
	Icarus Verilog
$end
$timescale
	1s
$end
$scope module alu_tb $end
$var wire 32 ! aluout [31:0] $end
$var reg 32 " aluin1 [31:0] $end
$var reg 32 # aluin2 [31:0] $end
$var reg 4 $ funct_alu [3:0] $end
$scope module test $end
$var wire 32 % aluin1 [31:0] $end
$var wire 32 & aluin2 [31:0] $end
$var wire 4 ' funct_alu [3:0] $end
$var wire 32 ( aluout [31:0] $end
$scope function calc $end
$var reg 32 ) aluin1 [31:0] $end
$var reg 32 * aluin2 [31:0] $end
$var reg 32 + calc [31:0] $end
$var reg 4 , funct_alu [3:0] $end
$upscope $end
$upscope $end
$scope task assert_calc $end
$var reg 32 - a [31:0] $end
$var reg 32 . b [31:0] $end
$var reg 80 / message [0:79] $end
$upscope $end
$upscope $end
$enddefinitions $end
#0
$dumpvars
bx /
bx .
bx -
b0 ,
b0 +
b0 *
b0 )
b0 (
b0 '
b0 &
b0 %
b0 $
b0 #
b0 "
b0 !
$end
#1
b100001 !
b100001 (
b100001 +
b1010 *
b10111 )
b1010 #
b1010 &
b10111 "
b10111 %
#3
b10000010100010001000100 /
b100001 .
b100001 -
#4
b1101 !
b1101 (
b1101 +
b1000 ,
b1000 $
b1000 '
#5
b10100110101010101000010 /
b1101 .
b1101 -
#6
b101110000000000 !
b101110000000000 (
b101110000000000 +
b1 ,
b1 $
b1 '
#7
b101001101001100010011000010111101010011010011000100110001001001 /
b101110000000000 .
b101110000000000 -
#8
b1001 ,
b1001 $
b1001 '
#10
b11101 !
b11101 (
b11101 +
b100 ,
b100 $
b100 '
#11
b10110000100111101010010 /
b11101 .
b11101 -
#12
b1100 ,
b1100 $
b1100 '
#14
b11111 !
b11111 (
b11111 +
b110 ,
b110 $
b110 '
#15
b100111101010010 /
b11111 .
b11111 -
#16
b1110 ,
b1110 $
b1110 '
#18
b10 !
b10 (
b10 +
b111 ,
b111 $
b111 '
#19
b10000010100111001000100 /
b10 .
b10 -
#20
b1111 ,
b1111 $
b1111 '
#22
b1 !
b1 (
b1 +
b11 *
b10000000000000000000000000010101 )
b11 #
b11 &
b10000000000000000000000000010101 "
b10000000000000000000000000010101 %
#23
b10000000000000000000000000010 !
b10000000000000000000000000010 (
b10000000000000000000000000010 +
b101 ,
b101 $
b101 '
#24
b101001101010010010011000010111101010011010100100100110001001001 /
b10000000000000000000000000010 .
b10000000000000000000000000010 -
#25
b11110000000000000000000000000010 !
b11110000000000000000000000000010 (
b11110000000000000000000000000010 +
b1101 ,
b1101 $
b1101 '
#26
b101001101010010010000010010111101010011010100100100000101001001 /
b11110000000000000000000000000010 .
b11110000000000000000000000000010 -
#27
b11111111111111111100000000000000 !
b11111111111111111100000000000000 (
b11111111111111111100000000000000 +
b10000000000000000000000000010001 *
b10000000000000000000000000010001 #
b10000000000000000000000000010001 &
#29
b11111111111111111100000000000000 .
b11111111111111111100000000000000 -
#30
b11000000000000000000000000001010 !
b11000000000000000000000000001010 (
b11000000000000000000000000001010 +
b10000000000000000000000000000001 *
b10000000000000000000000000000001 #
b10000000000000000000000000000001 &
#32
b11000000000000000000000000001010 .
b11000000000000000000000000001010 -
#33
b11110000000000000000000000000010 !
b11110000000000000000000000000010 (
b11110000000000000000000000000010 +
b11 *
b11 #
b11 &
#34
bx !
bx (
bx +
b11 ,
b11 $
b11 '
#35
b1111000011110000111100001111000 /
bx .
bx -
